{"scene":{"camera":{"position":{"x":25,"y":50,"z":40},"lookAt":{"x":0,"y":0,"z":0}}},"snaps":{"walls":{"y":0.75,"step":3,"offset":{"x":1,"z":-1},"rotationLockedAxes":["x","z"],"rotationNodes":"grid"},"pieces":{"y":1.25,"step":3,"offset":0,"rotationNodes":"grid"}},"templates":{"square":{"src":{"top":"#8B4513","dimensions":{"depth":2,"width":2,"height":0.5}},"position":{"x":"$x","y":0.75,"z":"$z"},"moveable":false},"endFeature":{"src":{"top":"#3E2723","dimensions":{"depth":5,"width":2,"height":0.75}},"position":{"x":"$x","y":0.75,"z":"$z"},"moveable":false},"corner":{"src":{"top":"#3E2723","dimensions":{"depth":5,"width":2,"height":0.75}},"position":{"x":"$x","y":0.75,"z":"$z"},"moveable":false},"wall":{"src":{"top":"#D7C7B3","left":"#D7C7B3","right":"#D7C7B3","dimensions":{"depth":5,"width":1,"height":2.5}},"position":{"x":"$x","y":0.75,"z":"$z"},"snap":"walls","moveable":true},"piece":{"src":{"top":"$color","side":"$color","dimensions":{"radius":0.75,"height":1}},"position":{"x":0,"y":1.25,"z":"$z"},"snap":"pieces","moveable":true}},"repeatedModels":{"Square$i":{"template":"square","x":{"start":-13,"stop":11,"step":3},"z":{"start":-13,"stop":11,"step":3}},"endFeature$i":{"template":"endFeature","x":{"start":-13,"stop":11,"step":3},"z":[-19,14]},"corner$i":{"template":"corner","x":[-16,14],"z":[-19,14]},"wall$i":{"template":"wall","x":{"start":-14,"stop":14,"step":3},"z":[-19,14]}},"models":{"base":{"src":{"top":"#3E2723","dimensions":{"depth":38,"width":32,"height":0.75}},"position":{"x":-16,"y":0,"z":-19},"moveable":false},"Piece1":{"template":"piece","color":"rgb(130, 22, 5)","z":-12.5},"Piece2":{"template":"piece","color":"#CD853F","z":11.75}}}